sansmic/app.py
sansmic/libsansmic.cpython-39-x86_64-linux-gnu.so
sansmic/model.py
sansmic/io.py
sansmic/__init__.py
sansmic/empirical.py
sansmic/_version.py
sansmic-1.0.7.dist-info/top_level.txt
sansmic-1.0.7.dist-info/RECORD
sansmic-1.0.7.dist-info/LICENSE
sansmic-1.0.7.dist-info/entry_points.txt
sansmic-1.0.7.dist-info/AUTHORS.md
sansmic-1.0.7.dist-info/METADATA
sansmic-1.0.7.dist-info/WHEEL
