Metadata-Version: 2.1
Name: sansmic
Version: 1.0.7
Summary: Sandia solution mining modeling software
Author: National Technology & Engineering Solutions of Sandia, LLC (NTESS), SANSMIC Authors (see AUTHORS.md)
Maintainer-email: David Hart <david.hart@sandia.gov>
Project-URL: Documentation, https://sandialabs.github.io/sansmic
Project-URL: Issues, https://github.com/sandialabs/sansmic/issues
Project-URL: Repository, https://github.com/sandialabs/sansmic.git
Classifier: Development Status :: 4 - Beta
Classifier: License :: OSI Approved :: BSD License
Classifier: Intended Audience :: End Users/Desktop
Classifier: Intended Audience :: Science/Research
Classifier: Programming Language :: Python :: 3
Classifier: Programming Language :: Python :: 3.9
Classifier: Programming Language :: Python :: 3.10
Classifier: Programming Language :: Python :: 3.11
Classifier: Programming Language :: Python :: 3.12
Classifier: Programming Language :: C++
Classifier: Topic :: Scientific/Engineering
Requires-Python: >=3.9
License-File: LICENSE
License-File: AUTHORS.md
Requires-Dist: numpy
Requires-Dist: pandas
Requires-Dist: click
Requires-Dist: tomli ; python_version < "3.11"
Provides-Extra: devel
Requires-Dist: pyyaml ; extra == 'devel'
Requires-Dist: pre-commit ; extra == 'devel'
Requires-Dist: pyproject-hooks ; extra == 'devel'
Requires-Dist: pytest ; extra == 'devel'
Requires-Dist: pytest-cov ; extra == 'devel'
Requires-Dist: black ; extra == 'devel'
Requires-Dist: pybind11 ; extra == 'devel'
Requires-Dist: nbmake ; extra == 'devel'
Requires-Dist: matplotlib ; extra == 'devel'
Requires-Dist: python-semantic-release ; extra == 'devel'
Provides-Extra: docs
Requires-Dist: Sphinx ; extra == 'docs'
Requires-Dist: pydata-sphinx-theme ; extra == 'docs'
Requires-Dist: sphinx-design ; extra == 'docs'
Requires-Dist: sphinxcontrib-bibtex ; extra == 'docs'
Requires-Dist: breathe ; extra == 'docs'
Requires-Dist: exhale ; extra == 'docs'
Requires-Dist: sphinx-click ; extra == 'docs'
Provides-Extra: examples
Requires-Dist: nbmake ; extra == 'examples'
Requires-Dist: matplotlib ; extra == 'examples'
Provides-Extra: formats
Requires-Dist: h5py ; extra == 'formats'
Requires-Dist: openpyxl ; extra == 'formats'
Requires-Dist: tabulate ; extra == 'formats'
Requires-Dist: pyyaml ; extra == 'formats'
Requires-Dist: lasio ; extra == 'formats'
Provides-Extra: tests
Requires-Dist: pytest ; extra == 'tests'
Requires-Dist: pytest-cov ; extra == 'tests'
